LICENSE
MANIFEST.in
README.md
setup.py
pybsrnqc/__init__.py
pybsrnqc/automaticQC.py
pybsrnqc/callbackSave.js
pybsrnqc/callbackSelect.js
pybsrnqc/coef_calculator.py
pybsrnqc/coef_study.py
pybsrnqc/config.py
pybsrnqc/open_data.py
pybsrnqc/plot_limits.py
pybsrnqc/qc_functions.py
pybsrnqc/qcrad.py
pybsrnqc/qcrad_conf.json
pybsrnqc/utils.py
pybsrnqc/visualPlot.py
pybsrnqc.egg-info/PKG-INFO
pybsrnqc.egg-info/SOURCES.txt
pybsrnqc.egg-info/dependency_links.txt
pybsrnqc.egg-info/requires.txt
pybsrnqc.egg-info/top_level.txt