Metadata-Version: 2.1
Name: pybsrnqc
Version: 0.2.1
Summary: Package to study BSRN data and their quality control
Home-page: https://github.com/LE2P/pybsrnqc/tree/main/pybsrnqc
Author: Maelle Baronnet
Author-email: maelle.baronnet@gmail.com
License: MIT
Platform: UNKNOWN
Classifier: Development Status :: 1 - Planning
Classifier: Intended Audience :: Science/Research
Classifier: License :: OSI Approved :: BSD License
Classifier: Operating System :: POSIX :: Linux
Classifier: Programming Language :: Python :: 2
Classifier: Programming Language :: Python :: 2.7
Classifier: Programming Language :: Python :: 3
Classifier: Programming Language :: Python :: 3.4
Classifier: Programming Language :: Python :: 3.5
License-File: LICENSE
